[{"id":"123","title":"Motorola One Power","imageURL":"https://cdn57.androidauthority.net/wp-content/uploads/2018/08/moto-one-power-official-840x472.jpg","price":"199.99","description":"This is a beast Android based mobile device."},{"id":"0.884159193084465","title":"iPhone XR","imageURL":"https://photos5.appleinsider.com/gallery/32708-56338-Apple_iphone_11-rosette-family-lineup-091019-xl.jpg","price":"649.99","description":"iPhone XR is a pocket friendly version for iPhone X series."},{"title":"Pixel 4a","imageURL":"https://fdn.gsmarena.com/imgroot/news/20/05/canceled-pixel-4a-xl/-727/gsmarena_002.jpg","price":"499.99","description":"Latest model of Google Pixel series","id":"0.011490178840543264"}]